HulianwangJavaGongchengshiJinjieZhishiWanquanSaomang/README.md
HulianwangJavaGongchengshiJinjieZhishiWanquanSaomang/__init__.py
HulianwangJavaGongchengshiJinjieZhishiWanquanSaomang/__main__.py
HulianwangJavaGongchengshiJinjieZhishiWanquanSaomang/file.epub
HulianwangJavaGongchengshiJinjieZhishiWanquanSaomang/index.html
HulianwangJavaGongchengshiJinjieZhishiWanquanSaomang/css/__init__.py
HulianwangJavaGongchengshiJinjieZhishiWanquanSaomang/css/annotations.css
HulianwangJavaGongchengshiJinjieZhishiWanquanSaomang/css/main.css
HulianwangJavaGongchengshiJinjieZhishiWanquanSaomang/css/normalize.css
HulianwangJavaGongchengshiJinjieZhishiWanquanSaomang/css/popup.css
HulianwangJavaGongchengshiJinjieZhishiWanquanSaomang/font/__init__.py
HulianwangJavaGongchengshiJinjieZhishiWanquanSaomang/font/fontello.eot
HulianwangJavaGongchengshiJinjieZhishiWanquanSaomang/font/fontello.svg
HulianwangJavaGongchengshiJinjieZhishiWanquanSaomang/font/fontello.ttf
HulianwangJavaGongchengshiJinjieZhishiWanquanSaomang/font/fontello.woff
HulianwangJavaGongchengshiJinjieZhishiWanquanSaomang/img/__init__.py
HulianwangJavaGongchengshiJinjieZhishiWanquanSaomang/img/annotator-glyph-sprite.png
HulianwangJavaGongchengshiJinjieZhishiWanquanSaomang/img/annotator-icon-sprite.png
HulianwangJavaGongchengshiJinjieZhishiWanquanSaomang/img/apple-touch-icon.png
HulianwangJavaGongchengshiJinjieZhishiWanquanSaomang/img/cancelfullscreen.png
HulianwangJavaGongchengshiJinjieZhishiWanquanSaomang/img/close.png
HulianwangJavaGongchengshiJinjieZhishiWanquanSaomang/img/fullscreen.png
HulianwangJavaGongchengshiJinjieZhishiWanquanSaomang/img/loader.gif
HulianwangJavaGongchengshiJinjieZhishiWanquanSaomang/img/menu-icon.png
HulianwangJavaGongchengshiJinjieZhishiWanquanSaomang/img/save.png
HulianwangJavaGongchengshiJinjieZhishiWanquanSaomang/img/saved.png
HulianwangJavaGongchengshiJinjieZhishiWanquanSaomang/img/settings-s.png
HulianwangJavaGongchengshiJinjieZhishiWanquanSaomang/img/settings.png
hulianwang_java_gongchengshi_jinjie_zhishi_wanquan_saomang-2024.3.6.0.dist-info/METADATA
hulianwang_java_gongchengshi_jinjie_zhishi_wanquan_saomang-2024.3.6.0.dist-info/WHEEL
hulianwang_java_gongchengshi_jinjie_zhishi_wanquan_saomang-2024.3.6.0.dist-info/entry_points.txt
hulianwang_java_gongchengshi_jinjie_zhishi_wanquan_saomang-2024.3.6.0.dist-info/top_level.txt
hulianwang_java_gongchengshi_jinjie_zhishi_wanquan_saomang-2024.3.6.0.dist-info/RECORD
